termipass/__init__.py
termipass/termipass.py
termipass-0.4.3.dist-info/METADATA
termipass-0.4.3.dist-info/WHEEL
termipass-0.4.3.dist-info/top_level.txt
termipass-0.4.3.dist-info/RECORD
