Metadata-Version: 2.1
Name: termipass
Version: 0.4.3
Summary: provides secure displays **** for password input for both Windows and Unix-like systems.
Author: Mahmoud Raouf
Author-email: mahmoud.raouf21@gmail.com
License: MIT
Classifier: Intended Audience :: Developers
Classifier: Operating System :: OS Independent
Classifier: Programming Language :: Python :: 3
